ci/transparency/spec/__init__.py
ci/transparency/spec/_version.py
ci/transparency/spec/__pycache__/__init__.cpython-311.pyc
ci/transparency/spec/schemas/provenance_tag.schema.json
ci/transparency/spec/schemas/series.schema.json
ci/transparency/spec/schemas/transparency_api.openapi.yaml
civic_transparency_spec-0.2.1.dist-info/licenses/LICENSE
civic_transparency_spec-0.2.1.dist-info/METADATA
civic_transparency_spec-0.2.1.dist-info/WHEEL
civic_transparency_spec-0.2.1.dist-info/top_level.txt
civic_transparency_spec-0.2.1.dist-info/RECORD
